{"task": "0_Sheikh_One_Color_Multiply_by_two_l6bkmzmkvfs83xelwq8", "user_id": "l79ss4khfexgmepa4xv_seungeon", "action_sequence": [{"action": {"tool": "start"}, "grid": [[0, 0, 0, 0, 0], [0, 0, 0, 0, 0], [0, 0, 0, 0, 0], [0, 0, 0, 0, 0], [0, 0, 0, 0, 0]], "currentLayer": 0, "layer_list": [[[0, 0, 0, 0, 0], [0, 0, 0, 0, 0], [0, 0, 0, 0, 0], [0, 0, 0, 0, 0], [0, 0, 0, 0, 0]]], "submit": 0, "time": 20}, {"action": {"tool": "copyFromInput"}, "grid": [[0, 0, 0, 0, 0], [0, 0, 0, 0, 0], ["0", 0, 0, 0, 0], ["1", "1", "1", 0, "1"], ["1", "1", "1", "1", "1"]], "currentLayer": 0, "layer_list": [[[0, 0, 0, 0, 0], [0, 0, 0, 0, 0], [0, 0, 0, 0, 0], ["1", "1", "1", 0, "1"], ["1", "1", "1", "1", "1"]]], "submit": 0, "time": 13}, {"action": {"tool": "select_fill", "selected_cells": [{"row": "1", "col": "0", "val": "1"}, {"row": "1", "col": "0", "val": "1"}, {"row": "1", "col": "1", "val": "1"}, {"row": "1", "col": "1", "val": "1"}, {"row": "1", "col": "2", "val": "1"}, {"row": "1", "col": "2", "val": "1"}, {"row": "1", "col": "4", "val": "1"}, {"row": "1", "col": "4", "val": "1"}, {"row": "2", "col": "0", "val": "1"}, {"row": "2", "col": "0", "val": "1"}, {"row": "2", "col": "1", "val": "1"}, {"row": "2", "col": "1", "val": "1"}, {"row": "2", "col": "2", "val": "1"}, {"row": "2", "col": "2", "val": "1"}, {"row": "2", "col": "4", "val": "1"}, {"row": "2", "col": "4", "val": "1"}, {"row": "3", "col": "3", "val": "1"}, {"row": "3", "col": "3", "val": "1"}]}, "grid": [[0, 0, 0, 0, 0], ["1", "1", "1", 0, "1"], ["1", "1", "1", 0, "1"], ["1", "1", "1", "1", "1"], ["1", "1", "1", "1", "1"]], "currentLayer": 0, "layer_list": [[[0, 0, 0, 0, 0], ["1", "1", "1", 0, "1"], ["1", "1", "1", 0, "1"], ["1", "1", "1", "1", "1"], ["1", "1", "1", "1", "1"]]], "submit": 1, "time": 10162}]}