{"task": "1_Sheikh_Simple_Color_Switch_l6abh4s781pwfrie9vt", "user_id": "l79ss4khfexgmepa4xv_seungeon", "action_sequence": [{"action": {"tool": "start"}, "grid": [[0, 0, 0, 0, 0], [0, 0, 0, 0, 0], [0, 0, 0, 0, 0], [0, 0, 0, 0, 0], [0, 0, 0, 0, 0]], "currentLayer": 0, "layer_list": [[[0, 0, 0, 0, 0], [0, 0, 0, 0, 0], [0, 0, 0, 0, 0], [0, 0, 0, 0, 0], [0, 0, 0, 0, 0]]], "submit": 0, "time": 14}, {"action": {"tool": "copyFromInput"}, "grid": [["4", 0, 0, 0, "1"], [0, "4", 0, "1", 0], [0, 0, "8", 0, 0], [0, "1", 0, "4", 0], ["1", 0, 0, 0, "4"]], "currentLayer": 0, "layer_list": [[["4", 0, 0, 0, "1"], [0, "4", 0, "1", 0], [0, 0, "8", 0, 0], [0, "1", 0, "4", 0], ["1", 0, 0, 0, "4"]]], "submit": 0, "time": 7}, {"action": {"tool": "rotate", "selected_cells": [{"row": 0, "col": 0, "val": "4", "selected": true}, {"row": 0, "col": 4, "val": "1", "selected": true}, {"row": 1, "col": 1, "val": "4", "selected": true}, {"row": 1, "col": 3, "val": "1", "selected": true}, {"row": 2, "col": 2, "val": "8", "selected": true}, {"row": 3, "col": 1, "val": "1", "selected": true}, {"row": 3, "col": 3, "val": "4", "selected": true}, {"row": 4, "col": 0, "val": "1", "selected": true}, {"row": 4, "col": 4, "val": "4", "selected": true}]}, "grid": [["1", 0, 0, 0, "4"], [0, "1", 0, "4", 0], [0, 0, "8", 0, 0], [0, "4", 0, "1", 0], ["4", 0, 0, 0, "1"]], "currentLayer": 0, "layer_list": [[["1", 0, 0, 0, "4"], [0, "1", 0, "4", 0], [0, 0, "8", 0, 0], [0, "4", 0, "1", 0], ["4", 0, 0, 0, "1"]]], "submit": 1, "time": 3039}]}