{"task": "24_Sheikh_Simple_Box_Moving_l6aapas5si5cuue2txa", "user_id": "l79soaxqr7xux8mmz1o_Wenchao", "action_sequence": [{"action": {"tool": "start"}, "grid": [[0, 0, 0, 0, 0], [0, 0, 0, 0, 0], [0, 0, 0, 0, 0], [0, 0, 0, 0, 0], [0, 0, 0, 0, 0]], "currentLayer": 0, "layer_list": [[[0, 0, 0, 0, 0], [0, 0, 0, 0, 0], [0, 0, 0, 0, 0], [0, 0, 0, 0, 0], [0, 0, 0, 0, 0]]], "submit": 0, "time": 14}, {"action": {"tool": "copyFromInput"}, "grid": [[0, "3", "7", "3", 0], [0, 0, "3", 0, 0], [0, 0, "0", 0, 0], [0, 0, "0", 0, 0], [0, 0, "0", 0, 0]], "currentLayer": 0, "layer_list": [[[0, "3", "7", "3", 0], [0, 0, "3", 0, 0], [0, 0, 0, 0, 0], [0, 0, 0, 0, 0], [0, 0, 0, 0, 0]]], "submit": 0, "time": 4}, {"action": {"tool": "select_fill", "selected_cells": [{"row": "2", "col": "2", "val": "7"}, {"row": "2", "col": "2", "val": "7"}, {"row": "3", "col": "2", "val": "7"}, {"row": "3", "col": "2", "val": "7"}, {"row": "4", "col": "2", "val": "7"}, {"row": "4", "col": "2", "val": "7"}]}, "grid": [[0, "3", "7", "3", 0], [0, 0, "3", 0, 0], [0, 0, "7", 0, 0], [0, 0, "7", 0, 0], [0, 0, "7", 0, 0]], "currentLayer": 0, "layer_list": [[[0, "3", "7", "3", 0], [0, 0, "3", 0, 0], [0, 0, "7", 0, 0], [0, 0, "7", 0, 0], [0, 0, "7", 0, 0]]], "submit": 0, "time": 10298}, {"action": {"tool": "select_fill", "selected_cells": [{"row": "2", "col": "2", "val": "0"}, {"row": "2", "col": "2", "val": "0"}, {"row": "3", "col": "2", "val": "0"}, {"row": "3", "col": "2", "val": "0"}, {"row": "4", "col": "2", "val": "0"}, {"row": "4", "col": "2", "val": "0"}]}, "grid": [[0, "3", "7", "3", 0], [0, 0, "3", 0, 0], [0, 0, 0, 0, 0], [0, 0, 0, 0, 0], [0, 0, 0, 0, 0]], "currentLayer": 0, "layer_list": [[[0, "3", "7", "3", 0], [0, 0, "3", 0, 0], [0, 0, 0, 0, 0], [0, 0, 0, 0, 0], [0, 0, 0, 0, 0]]], "submit": 0, "time": 1080}, {"action": {"tool": "select_fill", "selected_cells": [{"row": "2", "col": "2", "val": "7"}, {"row": "2", "col": "2", "val": "7"}, {"row": "3", "col": "2", "val": "7"}, {"row": "3", "col": "2", "val": "7"}, {"row": "4", "col": "2", "val": "7"}, {"row": "4", "col": "2", "val": "7"}]}, "grid": [[0, "3", "7", "3", 0], [0, 0, "3", 0, 0], [0, 0, "7", 0, 0], [0, 0, "7", 0, 0], [0, 0, "7", 0, 0]], "currentLayer": 0, "layer_list": [[[0, "3", "7", "3", 0], [0, 0, "3", 0, 0], [0, 0, "7", 0, 0], [0, 0, "7", 0, 0], [0, 0, "7", 0, 0]]], "submit": 0, "time": 1418}, {"action": {"tool": "select_fill", "selected_cells": [{"row": "0", "col": "2", "val": "0"}, {"row": "0", "col": "2", "val": "0"}]}, "grid": [[0, "3", 0, "3", 0], [0, 0, "3", 0, 0], [0, 0, "7", 0, 0], [0, 0, "7", 0, 0], [0, 0, "7", 0, 0]], "currentLayer": 0, "layer_list": [[[0, "3", 0, "3", 0], [0, 0, "3", 0, 0], [0, 0, "7", 0, 0], [0, 0, "7", 0, 0], [0, 0, "7", 0, 0]]], "submit": 1, "time": 2600}]}