{"task": "50cb2852", "user_id": "l6a8xkmmvb3jkomn2x9", "action_sequence": [{"action": {"tool": "change_example", "example": 1}, "grid": [[0, 0, 0], [0, 0, 0], [0, 0, 0]], "currentLayer": 0, "layer_list": [[[0, 0, 0], [0, 0, 0], [0, 0, 0]]], "time": 2978}, {"action": {"tool": "change_example", "example": 0}, "grid": [[0, 0, 0], [0, 0, 0], [0, 0, 0]], "currentLayer": 0, "layer_list": [[[0, 0, 0], [0, 0, 0], [0, 0, 0]]], "time": 1026}, {"action": {"tool": "change_example", "example": 1}, "grid": [[0, 0, 0], [0, 0, 0], [0, 0, 0]], "currentLayer": 0, "layer_list": [[[0, 0, 0], [0, 0, 0], [0, 0, 0]]], "time": 773}, {"action": {"tool": "change_example", "example": 2}, "grid": [[0, 0, 0], [0, 0, 0], [0, 0, 0]], "currentLayer": 0, "layer_list": [[[0, 0, 0], [0, 0, 0], [0, 0, 0]]], "time": 217}, {"action": {"tool": "change_example", "example": 1}, "grid": [[0, 0, 0], [0, 0, 0], [0, 0, 0]], "currentLayer": 0, "layer_list": [[[0, 0, 0], [0, 0, 0], [0, 0, 0]]], "time": 1050}, {"action": {"tool": "change_example", "example": 0}, "grid": [[0, 0, 0], [0, 0, 0], [0, 0, 0]], "currentLayer": 0, "layer_list": [[[0, 0, 0], [0, 0, 0], [0, 0, 0]]], "time": 330}, {"action": {"tool": "copyFromInput"}, "grid": [[0, 1, 1, 1, 1, 1, 0, 0, 0, 0, 0, 0, 0], [0, 1, 1, 1, 1, 1, 0, 0, 1, 1, 1, 0, 0], [0, 1, 1, 1, 1, 1, 0, 0, 1, 1, 1, 0, 0], [0, 1, 1, 1, 1, 1, 0, 0, 1, 1, 1, 0, 0], [0, 0, 0, 0, 0, 0, 0, 0, 0, 0, 0, 0, 0], [0, 0, 2, 2, 2, 2, 2, 2, 0, 0, 0, 0, 0], [0, 0, 2, 2, 2, 2, 2, 2, 0, 0, 0, 0, 0], [0, 0, 2, 2, 2, 2, 2, 2, 0, 3, 3, 3, 3], [0, 0, 2, 2, 2, 2, 2, 2, 0, 3, 3, 3, 3], [0, 0, 2, 2, 2, 2, 2, 2, 0, 3, 3, 3, 3], [0, 0, 2, 2, 2, 2, 2, 2, 0, 3, 3, 3, 3], [0, 0, 0, 0, 0, 0, 0, 0, 0, 3, 3, 3, 3], [0, 0, 0, 0, 0, 0, 0, 0, 0, 3, 3, 3, 3], [0, 0, 0, 0, 0, 0, 0, 0, 0, 3, 3, 3, 3]], "currentLayer": 0, "layer_list": [[[0, 1, 1, 1, 1, 1, 0, 0, 0, 0, 0, 0, 0], [0, 1, 1, 1, 1, 1, 0, 0, 1, 1, 1, 0, 0], [0, 1, 1, 1, 1, 1, 0, 0, 1, 1, 1, 0, 0], [0, 1, 1, 1, 1, 1, 0, 0, 1, 1, 1, 0, 0], [0, 0, 0, 0, 0, 0, 0, 0, 0, 0, 0, 0, 0], [0, 0, 2, 2, 2, 2, 2, 2, 0, 0, 0, 0, 0], [0, 0, 2, 2, 2, 2, 2, 2, 0, 0, 0, 0, 0], [0, 0, 2, 2, 2, 2, 2, 2, 0, 3, 3, 3, 3], [0, 0, 2, 2, 2, 2, 2, 2, 0, 3, 3, 3, 3], [0, 0, 2, 2, 2, 2, 2, 2, 0, 3, 3, 3, 3], [0, 0, 2, 2, 2, 2, 2, 2, 0, 3, 3, 3, 3], [0, 0, 0, 0, 0, 0, 0, 0, 0, 3, 3, 3, 3], [0, 0, 0, 0, 0, 0, 0, 0, 0, 3, 3, 3, 3], [0, 0, 0, 0, 0, 0, 0, 0, 0, 3, 3, 3, 3]]], "time": 735}, {"action": {"tool": "select_fill", "selected_cells": [{"row": "1", "col": "2", "val": "8"}, {"row": "1", "col": "3", "val": "8"}, {"row": "1", "col": "4", "val": "8"}, {"row": "2", "col": "2", "val": "8"}, {"row": "2", "col": "3", "val": "8"}, {"row": "2", "col": "4", "val": "8"}]}, "grid": [[0, 1, 1, 1, 1, 1, 0, 0, 0, 0, 0, 0, 0], [0, 1, 1, 1, 1, 1, 0, 0, 1, 1, 1, 0, 0], [0, 1, 1, 1, 1, 1, 0, 0, 1, 1, 1, 0, 0], [0, 1, 1, 1, 1, 1, 0, 0, 1, 1, 1, 0, 0], [0, 0, 0, 0, 0, 0, 0, 0, 0, 0, 0, 0, 0], [0, 0, 2, 2, 2, 2, 2, 2, 0, 0, 0, 0, 0], [0, 0, 2, 2, 2, 2, 2, 2, 0, 0, 0, 0, 0], [0, 0, 2, 2, 2, 2, 2, 2, 0, 3, 3, 3, 3], [0, 0, 2, 2, 2, 2, 2, 2, 0, 3, 3, 3, 3], [0, 0, 2, 2, 2, 2, 2, 2, 0, 3, 3, 3, 3], [0, 0, 2, 2, 2, 2, 2, 2, 0, 3, 3, 3, 3], [0, 0, 0, 0, 0, 0, 0, 0, 0, 3, 3, 3, 3], [0, 0, 0, 0, 0, 0, 0, 0, 0, 3, 3, 3, 3], [0, 0, 0, 0, 0, 0, 0, 0, 0, 3, 3, 3, 3]], "currentLayer": 0, "layer_list": [[[0, 1, 1, 1, 1, 1, 0, 0, 0, 0, 0, 0, 0], [0, 1, "8", "8", "8", 1, 0, 0, 1, 1, 1, 0, 0], [0, 1, "8", "8", "8", 1, 0, 0, 1, 1, 1, 0, 0], [0, 1, 1, 1, 1, 1, 0, 0, 1, 1, 1, 0, 0], [0, 0, 0, 0, 0, 0, 0, 0, 0, 0, 0, 0, 0], [0, 0, 2, 2, 2, 2, 2, 2, 0, 0, 0, 0, 0], [0, 0, 2, 2, 2, 2, 2, 2, 0, 0, 0, 0, 0], [0, 0, 2, 2, 2, 2, 2, 2, 0, 3, 3, 3, 3], [0, 0, 2, 2, 2, 2, 2, 2, 0, 3, 3, 3, 3], [0, 0, 2, 2, 2, 2, 2, 2, 0, 3, 3, 3, 3], [0, 0, 2, 2, 2, 2, 2, 2, 0, 3, 3, 3, 3], [0, 0, 0, 0, 0, 0, 0, 0, 0, 3, 3, 3, 3], [0, 0, 0, 0, 0, 0, 0, 0, 0, 3, 3, 3, 3], [0, 0, 0, 0, 0, 0, 0, 0, 0, 3, 3, 3, 3]]], "time": 3435}, {"action": {"tool": "select_fill", "selected_cells": [{"row": "6", "col": "3", "val": "8"}, {"row": "6", "col": "4", "val": "8"}, {"row": "6", "col": "5", "val": "8"}, {"row": "6", "col": "6", "val": "8"}, {"row": "7", "col": "3", "val": "8"}, {"row": "7", "col": "4", "val": "8"}, {"row": "7", "col": "5", "val": "8"}, {"row": "7", "col": "6", "val": "8"}, {"row": "8", "col": "3", "val": "8"}, {"row": "8", "col": "4", "val": "8"}, {"row": "8", "col": "5", "val": "8"}, {"row": "8", "col": "6", "val": "8"}, {"row": "9", "col": "3", "val": "8"}, {"row": "9", "col": "4", "val": "8"}, {"row": "9", "col": "5", "val": "8"}, {"row": "9", "col": "6", "val": "8"}]}, "grid": [[0, 1, 1, 1, 1, 1, 0, 0, 0, 0, 0, 0, 0], [0, 1, 1, 1, 1, 1, 0, 0, 1, 1, 1, 0, 0], [0, 1, 1, 1, 1, 1, 0, 0, 1, 1, 1, 0, 0], [0, 1, 1, 1, 1, 1, 0, 0, 1, 1, 1, 0, 0], [0, 0, 0, 0, 0, 0, 0, 0, 0, 0, 0, 0, 0], [0, 0, 2, 2, 2, 2, 2, 2, 0, 0, 0, 0, 0], [0, 0, 2, 2, 2, 2, 2, 2, 0, 0, 0, 0, 0], [0, 0, 2, 2, 2, 2, 2, 2, 0, 3, 3, 3, 3], [0, 0, 2, 2, 2, 2, 2, 2, 0, 3, 3, 3, 3], [0, 0, 2, 2, 2, 2, 2, 2, 0, 3, 3, 3, 3], [0, 0, 2, 2, 2, 2, 2, 2, 0, 3, 3, 3, 3], [0, 0, 0, 0, 0, 0, 0, 0, 0, 3, 3, 3, 3], [0, 0, 0, 0, 0, 0, 0, 0, 0, 3, 3, 3, 3], [0, 0, 0, 0, 0, 0, 0, 0, 0, 3, 3, 3, 3]], "currentLayer": 0, "layer_list": [[[0, 1, 1, 1, 1, 1, 0, 0, 0, 0, 0, 0, 0], [0, 1, "8", "8", "8", 1, 0, 0, 1, 1, 1, 0, 0], [0, 1, "8", "8", "8", 1, 0, 0, 1, 1, 1, 0, 0], [0, 1, 1, 1, 1, 1, 0, 0, 1, 1, 1, 0, 0], [0, 0, 0, 0, 0, 0, 0, 0, 0, 0, 0, 0, 0], [0, 0, 2, 2, 2, 2, 2, 2, 0, 0, 0, 0, 0], [0, 0, 2, "8", "8", "8", "8", 2, 0, 0, 0, 0, 0], [0, 0, 2, "8", "8", "8", "8", 2, 0, 3, 3, 3, 3], [0, 0, 2, "8", "8", "8", "8", 2, 0, 3, 3, 3, 3], [0, 0, 2, "8", "8", "8", "8", 2, 0, 3, 3, 3, 3], [0, 0, 2, 2, 2, 2, 2, 2, 0, 3, 3, 3, 3], [0, 0, 0, 0, 0, 0, 0, 0, 0, 3, 3, 3, 3], [0, 0, 0, 0, 0, 0, 0, 0, 0, 3, 3, 3, 3], [0, 0, 0, 0, 0, 0, 0, 0, 0, 3, 3, 3, 3]]], "time": 1937}, {"action": {"tool": "select_fill", "selected_cells": [{"row": "8", "col": "10", "val": "8"}, {"row": "8", "col": "11", "val": "8"}, {"row": "9", "col": "10", "val": "8"}, {"row": "9", "col": "11", "val": "8"}, {"row": "10", "col": "10", "val": "8"}, {"row": "10", "col": "11", "val": "8"}, {"row": "11", "col": "10", "val": "8"}, {"row": "11", "col": "11", "val": "8"}, {"row": "12", "col": "10", "val": "8"}, {"row": "12", "col": "11", "val": "8"}]}, "grid": [[0, 1, 1, 1, 1, 1, 0, 0, 0, 0, 0, 0, 0], [0, 1, 1, 1, 1, 1, 0, 0, 1, 1, 1, 0, 0], [0, 1, 1, 1, 1, 1, 0, 0, 1, 1, 1, 0, 0], [0, 1, 1, 1, 1, 1, 0, 0, 1, 1, 1, 0, 0], [0, 0, 0, 0, 0, 0, 0, 0, 0, 0, 0, 0, 0], [0, 0, 2, 2, 2, 2, 2, 2, 0, 0, 0, 0, 0], [0, 0, 2, 2, 2, 2, 2, 2, 0, 0, 0, 0, 0], [0, 0, 2, 2, 2, 2, 2, 2, 0, 3, 3, 3, 3], [0, 0, 2, 2, 2, 2, 2, 2, 0, 3, 3, 3, 3], [0, 0, 2, 2, 2, 2, 2, 2, 0, 3, 3, 3, 3], [0, 0, 2, 2, 2, 2, 2, 2, 0, 3, 3, 3, 3], [0, 0, 0, 0, 0, 0, 0, 0, 0, 3, 3, 3, 3], [0, 0, 0, 0, 0, 0, 0, 0, 0, 3, 3, 3, 3], [0, 0, 0, 0, 0, 0, 0, 0, 0, 3, 3, 3, 3]], "currentLayer": 0, "layer_list": [[[0, 1, 1, 1, 1, 1, 0, 0, 0, 0, 0, 0, 0], [0, 1, "8", "8", "8", 1, 0, 0, 1, 1, 1, 0, 0], [0, 1, "8", "8", "8", 1, 0, 0, 1, 1, 1, 0, 0], [0, 1, 1, 1, 1, 1, 0, 0, 1, 1, 1, 0, 0], [0, 0, 0, 0, 0, 0, 0, 0, 0, 0, 0, 0, 0], [0, 0, 2, 2, 2, 2, 2, 2, 0, 0, 0, 0, 0], [0, 0, 2, "8", "8", "8", "8", 2, 0, 0, 0, 0, 0], [0, 0, 2, "8", "8", "8", "8", 2, 0, 3, 3, 3, 3], [0, 0, 2, "8", "8", "8", "8", 2, 0, 3, "8", "8", 3], [0, 0, 2, "8", "8", "8", "8", 2, 0, 3, "8", "8", 3], [0, 0, 2, 2, 2, 2, 2, 2, 0, 3, "8", "8", 3], [0, 0, 0, 0, 0, 0, 0, 0, 0, 3, "8", "8", 3], [0, 0, 0, 0, 0, 0, 0, 0, 0, 3, "8", "8", 3], [0, 0, 0, 0, 0, 0, 0, 0, 0, 3, 3, 3, 3]]], "time": 3103}, {"action": {"tool": "select_fill", "selected_cells": [{"row": "2", "col": "9", "val": "8"}]}, "grid": [[0, 1, 1, 1, 1, 1, 0, 0, 0, 0, 0, 0, 0], [0, 1, 1, 1, 1, 1, 0, 0, 1, 1, 1, 0, 0], [0, 1, 1, 1, 1, 1, 0, 0, 1, 1, 1, 0, 0], [0, 1, 1, 1, 1, 1, 0, 0, 1, 1, 1, 0, 0], [0, 0, 0, 0, 0, 0, 0, 0, 0, 0, 0, 0, 0], [0, 0, 2, 2, 2, 2, 2, 2, 0, 0, 0, 0, 0], [0, 0, 2, 2, 2, 2, 2, 2, 0, 0, 0, 0, 0], [0, 0, 2, 2, 2, 2, 2, 2, 0, 3, 3, 3, 3], [0, 0, 2, 2, 2, 2, 2, 2, 0, 3, 3, 3, 3], [0, 0, 2, 2, 2, 2, 2, 2, 0, 3, 3, 3, 3], [0, 0, 2, 2, 2, 2, 2, 2, 0, 3, 3, 3, 3], [0, 0, 0, 0, 0, 0, 0, 0, 0, 3, 3, 3, 3], [0, 0, 0, 0, 0, 0, 0, 0, 0, 3, 3, 3, 3], [0, 0, 0, 0, 0, 0, 0, 0, 0, 3, 3, 3, 3]], "currentLayer": 0, "layer_list": [[[0, 1, 1, 1, 1, 1, 0, 0, 0, 0, 0, 0, 0], [0, 1, "8", "8", "8", 1, 0, 0, 1, 1, 1, 0, 0], [0, 1, "8", "8", "8", 1, 0, 0, 1, "8", 1, 0, 0], [0, 1, 1, 1, 1, 1, 0, 0, 1, 1, 1, 0, 0], [0, 0, 0, 0, 0, 0, 0, 0, 0, 0, 0, 0, 0], [0, 0, 2, 2, 2, 2, 2, 2, 0, 0, 0, 0, 0], [0, 0, 2, "8", "8", "8", "8", 2, 0, 0, 0, 0, 0], [0, 0, 2, "8", "8", "8", "8", 2, 0, 3, 3, 3, 3], [0, 0, 2, "8", "8", "8", "8", 2, 0, 3, "8", "8", 3], [0, 0, 2, "8", "8", "8", "8", 2, 0, 3, "8", "8", 3], [0, 0, 2, 2, 2, 2, 2, 2, 0, 3, "8", "8", 3], [0, 0, 0, 0, 0, 0, 0, 0, 0, 3, "8", "8", 3], [0, 0, 0, 0, 0, 0, 0, 0, 0, 3, "8", "8", 3], [0, 0, 0, 0, 0, 0, 0, 0, 0, 3, 3, 3, 3]]], "time": 2069}, {"action": {"tool": "check", "correct": true}, "grid": [[0, 1, 1, 1, 1, 1, 0, 0, 0, 0, 0, 0, 0], [0, 1, 8, 8, 8, 1, 0, 0, 1, 1, 1, 0, 0], [0, 1, 8, 8, 8, 1, 0, 0, 1, 8, 1, 0, 0], [0, 1, 1, 1, 1, 1, 0, 0, 1, 1, 1, 0, 0], [0, 0, 0, 0, 0, 0, 0, 0, 0, 0, 0, 0, 0], [0, 0, 2, 2, 2, 2, 2, 2, 0, 0, 0, 0, 0], [0, 0, 2, 8, 8, 8, 8, 2, 0, 0, 0, 0, 0], [0, 0, 2, 8, 8, 8, 8, 2, 0, 3, 3, 3, 3], [0, 0, 2, 8, 8, 8, 8, 2, 0, 3, 8, 8, 3], [0, 0, 2, 8, 8, 8, 8, 2, 0, 3, 8, 8, 3], [0, 0, 2, 2, 2, 2, 2, 2, 0, 3, 8, 8, 3], [0, 0, 0, 0, 0, 0, 0, 0, 0, 3, 8, 8, 3], [0, 0, 0, 0, 0, 0, 0, 0, 0, 3, 8, 8, 3], [0, 0, 0, 0, 0, 0, 0, 0, 0, 3, 3, 3, 3]], "currentLayer": 0, "layer_list": [[[0, 1, 1, 1, 1, 1, 0, 0, 0, 0, 0, 0, 0], [0, 1, "8", "8", "8", 1, 0, 0, 1, 1, 1, 0, 0], [0, 1, "8", "8", "8", 1, 0, 0, 1, "8", 1, 0, 0], [0, 1, 1, 1, 1, 1, 0, 0, 1, 1, 1, 0, 0], [0, 0, 0, 0, 0, 0, 0, 0, 0, 0, 0, 0, 0], [0, 0, 2, 2, 2, 2, 2, 2, 0, 0, 0, 0, 0], [0, 0, 2, "8", "8", "8", "8", 2, 0, 0, 0, 0, 0], [0, 0, 2, "8", "8", "8", "8", 2, 0, 3, 3, 3, 3], [0, 0, 2, "8", "8", "8", "8", 2, 0, 3, "8", "8", 3], [0, 0, 2, "8", "8", "8", "8", 2, 0, 3, "8", "8", 3], [0, 0, 2, 2, 2, 2, 2, 2, 0, 3, "8", "8", 3], [0, 0, 0, 0, 0, 0, 0, 0, 0, 3, "8", "8", 3], [0, 0, 0, 0, 0, 0, 0, 0, 0, 3, "8", "8", 3], [0, 0, 0, 0, 0, 0, 0, 0, 0, 3, 3, 3, 3]]], "time": 736}]}