{"task": "94f9d214", "user_id": "l6a4nobxw4gw366bzc8", "action_sequence": [{"action": {"tool": "copyFromInput"}, "grid": [[0, 3, 0, 3], [3, 3, 3, 0], [0, 0, 0, 3], [3, 3, 3, 0], [0, 0, 1, 1], [0, 0, 1, 1], [0, 1, 0, 0], [1, 1, 0, 0]], "currentLayer": 0, "layer_list": [[[0, 3, 0, 3], [3, 3, 3, 0], [0, 0, 0, 3], [3, 3, 3, 0], [0, 0, 1, 1], [0, 0, 1, 1], [0, 1, 0, 0], [1, 1, 0, 0]]], "time": 3713}, {"action": {"tool": "resizeOutputGrid", "height": "4", "width": "4"}, "grid": [[0, 3, 0, 3], [3, 3, 3, 0], [0, 0, 0, 3], [3, 3, 3, 0]], "currentLayer": 0, "layer_list": [[[0, 3, 0, 3], [3, 3, 3, 0], [0, 0, 0, 3], [3, 3, 3, 0]]], "time": 2192}, {"action": {"tool": "edit", "symbol": "2", "row": "0", "col": "0"}, "grid": [[2, 3, 0, 3], [3, 3, 3, 0], [0, 0, 0, 3], [3, 3, 3, 0]], "currentLayer": 0, "layer_list": [[["2", 3, 0, 3], [3, 3, 3, 0], [0, 0, 0, 3], [3, 3, 3, 0]]], "time": 8788}, {"action": {"tool": "edit", "symbol": "2", "row": "2", "col": "0"}, "grid": [[2, 3, 0, 3], [3, 3, 3, 0], [2, 0, 0, 3], [3, 3, 3, 0]], "currentLayer": 0, "layer_list": [[["2", 3, 0, 3], [3, 3, 3, 0], ["2", 0, 0, 3], [3, 3, 3, 0]]], "time": 2273}, {"action": {"tool": "edit", "symbol": "2", "row": "2", "col": "2"}, "grid": [[2, 3, 0, 3], [3, 3, 3, 0], [2, 0, 2, 3], [3, 3, 3, 0]], "currentLayer": 0, "layer_list": [[["2", 3, 0, 3], [3, 3, 3, 0], ["2", 0, "2", 3], [3, 3, 3, 0]]], "time": 1733}, {"action": {"tool": "edit", "symbol": "2", "row": "3", "col": "3"}, "grid": [[2, 3, 0, 3], [3, 3, 3, 0], [2, 0, 2, 3], [3, 3, 3, 2]], "currentLayer": 0, "layer_list": [[["2", 3, 0, 3], [3, 3, 3, 0], ["2", 0, "2", 3], [3, 3, 3, "2"]]], "time": 1335}, {"action": {"tool": "edit", "symbol": "0", "row": "3", "col": "0"}, "grid": [[2, 3, 0, 3], [3, 3, 3, 0], [2, 0, 2, 3], [0, 3, 3, 2]], "currentLayer": 0, "layer_list": [[["2", 3, 0, 3], [3, 3, 3, 0], ["2", 0, "2", 3], [0, 3, 3, "2"]]], "time": 2242}, {"action": {"tool": "edit", "symbol": "0", "row": "3", "col": "1"}, "grid": [[2, 3, 0, 3], [3, 3, 3, 0], [2, 0, 2, 3], [0, 0, 3, 2]], "currentLayer": 0, "layer_list": [[["2", 3, 0, 3], [3, 3, 3, 0], ["2", 0, "2", 3], [0, 0, 3, "2"]]], "time": 240}, {"action": {"tool": "edit", "symbol": "0", "row": "3", "col": "2"}, "grid": [[2, 3, 0, 3], [3, 3, 3, 0], [2, 0, 2, 3], [0, 0, 0, 2]], "currentLayer": 0, "layer_list": [[["2", 3, 0, 3], [3, 3, 3, 0], ["2", 0, "2", 3], [0, 0, 0, "2"]]], "time": 346}, {"action": {"tool": "edit", "symbol": "0", "row": "2", "col": "3"}, "grid": [[2, 3, 0, 3], [3, 3, 3, 0], [2, 0, 2, 0], [0, 0, 0, 2]], "currentLayer": 0, "layer_list": [[["2", 3, 0, 3], [3, 3, 3, 0], ["2", 0, "2", 0], [0, 0, 0, "2"]]], "time": 270}, {"action": {"tool": "edit", "symbol": "0", "row": "0", "col": "3"}, "grid": [[2, 3, 0, 0], [3, 3, 3, 0], [2, 0, 2, 0], [0, 0, 0, 2]], "currentLayer": 0, "layer_list": [[["2", 3, 0, 0], [3, 3, 3, 0], ["2", 0, "2", 0], [0, 0, 0, "2"]]], "time": 261}, {"action": {"tool": "edit", "symbol": "0", "row": "1", "col": "2"}, "grid": [[2, 3, 0, 0], [3, 3, 0, 0], [2, 0, 2, 0], [0, 0, 0, 2]], "currentLayer": 0, "layer_list": [[["2", 3, 0, 0], [3, 3, 0, 0], ["2", 0, "2", 0], [0, 0, 0, "2"]]], "time": 256}, {"action": {"tool": "edit", "symbol": "0", "row": "0", "col": "1"}, "grid": [[2, 0, 0, 0], [3, 3, 0, 0], [2, 0, 2, 0], [0, 0, 0, 2]], "currentLayer": 0, "layer_list": [[["2", 0, 0, 0], [3, 3, 0, 0], ["2", 0, "2", 0], [0, 0, 0, "2"]]], "time": 256}, {"action": {"tool": "edit", "symbol": "0", "row": "1", "col": "1"}, "grid": [[2, 0, 0, 0], [3, 0, 0, 0], [2, 0, 2, 0], [0, 0, 0, 2]], "currentLayer": 0, "layer_list": [[["2", 0, 0, 0], [3, 0, 0, 0], ["2", 0, "2", 0], [0, 0, 0, "2"]]], "time": 209}, {"action": {"tool": "edit", "symbol": "0", "row": "1", "col": "0"}, "grid": [[2, 0, 0, 0], [0, 0, 0, 0], [2, 0, 2, 0], [0, 0, 0, 2]], "currentLayer": 0, "layer_list": [[["2", 0, 0, 0], [0, 0, 0, 0], ["2", 0, "2", 0], [0, 0, 0, "2"]]], "time": 255}, {"action": {"tool": "check", "correct": true}, "grid": [[2, 0, 0, 0], [0, 0, 0, 0], [2, 0, 2, 0], [0, 0, 0, 2]], "currentLayer": 0, "layer_list": [[["2", 0, 0, 0], [0, 0, 0, 0], ["2", 0, "2", 0], [0, 0, 0, "2"]]], "time": 441}]}