{"task": "b8cdaf2b", "user_id": "l6a4pssse3gxwgpf3ba", "action_sequence": [{"action": {"tool": "change_example", "example": 1}, "grid": [[0, 0, 0], [0, 0, 0], [0, 0, 0]], "currentLayer": 0, "layer_list": [[[0, 0, 0], [0, 0, 0], [0, 0, 0]]], "time": 95122}, {"action": {"tool": "change_example", "example": 2}, "grid": [[0, 0, 0], [0, 0, 0], [0, 0, 0]], "currentLayer": 0, "layer_list": [[[0, 0, 0], [0, 0, 0], [0, 0, 0]]], "time": 3700}, {"action": {"tool": "change_example", "example": 3}, "grid": [[0, 0, 0], [0, 0, 0], [0, 0, 0]], "currentLayer": 0, "layer_list": [[[0, 0, 0], [0, 0, 0], [0, 0, 0]]], "time": 1802}, {"action": {"tool": "change_example", "example": 2}, "grid": [[0, 0, 0], [0, 0, 0], [0, 0, 0]], "currentLayer": 0, "layer_list": [[[0, 0, 0], [0, 0, 0], [0, 0, 0]]], "time": 2798}, {"action": {"tool": "change_example", "example": 1}, "grid": [[0, 0, 0], [0, 0, 0], [0, 0, 0]], "currentLayer": 0, "layer_list": [[[0, 0, 0], [0, 0, 0], [0, 0, 0]]], "time": 152}, {"action": {"tool": "change_example", "example": 0}, "grid": [[0, 0, 0], [0, 0, 0], [0, 0, 0]], "currentLayer": 0, "layer_list": [[[0, 0, 0], [0, 0, 0], [0, 0, 0]]], "time": 148}, {"action": {"tool": "copyFromInput"}, "grid": [[0, 0, 0, 0, 0, 0, 0, 0, 0], [0, 0, 0, 0, 0, 0, 0, 0, 0], [0, 0, 0, 0, 0, 0, 0, 0, 0], [0, 0, 0, 0, 0, 0, 0, 0, 0], [0, 0, 0, 0, 0, 0, 0, 0, 0], [0, 0, 0, 0, 0, 0, 0, 0, 0], [0, 0, 0, 0, 0, 0, 0, 0, 0], [0, 0, 0, 8, 8, 8, 0, 0, 0], [8, 8, 8, 2, 2, 2, 8, 8, 8]], "currentLayer": 0, "layer_list": [[[0, 0, 0, 0, 0, 0, 0, 0, 0], [0, 0, 0, 0, 0, 0, 0, 0, 0], [0, 0, 0, 0, 0, 0, 0, 0, 0], [0, 0, 0, 0, 0, 0, 0, 0, 0], [0, 0, 0, 0, 0, 0, 0, 0, 0], [0, 0, 0, 0, 0, 0, 0, 0, 0], [0, 0, 0, 0, 0, 0, 0, 0, 0], [0, 0, 0, 8, 8, 8, 0, 0, 0], [8, 8, 8, 2, 2, 2, 8, 8, 8]]], "time": 4492}, {"action": {"tool": "select_fill", "selected_cells": []}, "grid": [[0, 0, 0, 0, 0, 0, 0, 0, 0], [0, 0, 0, 0, 0, 0, 0, 0, 0], [0, 0, 0, 0, 0, 0, 0, 0, 0], [0, 0, 0, 0, 0, 0, 0, 0, 0], [0, 0, 0, 0, 0, 0, 0, 0, 0], [0, 0, 0, 0, 0, 0, 0, 0, 0], [0, 0, 0, 0, 0, 0, 0, 0, 0], [0, 0, 0, 8, 8, 8, 0, 0, 0], [8, 8, 8, 2, 2, 2, 8, 8, 8]], "currentLayer": 0, "layer_list": [[[0, 0, 0, 0, 0, 0, 0, 0, 0], [0, 0, 0, 0, 0, 0, 0, 0, 0], [0, 0, 0, 0, 0, 0, 0, 0, 0], [0, 0, 0, 0, 0, 0, 0, 0, 0], [0, 0, 0, 0, 0, 0, 0, 0, 0], [0, 0, 0, 0, 0, 0, 0, 0, 0], [0, 0, 0, 0, 0, 0, 0, 0, 0], [0, 0, 0, 8, 8, 8, 0, 0, 0], [8, 8, 8, 2, 2, 2, 8, 8, 8]]], "time": 2477}, {"action": {"tool": "select_fill", "selected_cells": [{"row": "4", "col": "0", "val": "2"}, {"row": "4", "col": "8", "val": "2"}, {"row": "5", "col": "1", "val": "2"}, {"row": "5", "col": "7", "val": "2"}, {"row": "6", "col": "2", "val": "2"}, {"row": "6", "col": "6", "val": "2"}]}, "grid": [[0, 0, 0, 0, 0, 0, 0, 0, 0], [0, 0, 0, 0, 0, 0, 0, 0, 0], [0, 0, 0, 0, 0, 0, 0, 0, 0], [0, 0, 0, 0, 0, 0, 0, 0, 0], [0, 0, 0, 0, 0, 0, 0, 0, 0], [0, 0, 0, 0, 0, 0, 0, 0, 0], [0, 0, 0, 0, 0, 0, 0, 0, 0], [0, 0, 0, 8, 8, 8, 0, 0, 0], [8, 8, 8, 2, 2, 2, 8, 8, 8]], "currentLayer": 0, "layer_list": [[[0, 0, 0, 0, 0, 0, 0, 0, 0], [0, 0, 0, 0, 0, 0, 0, 0, 0], [0, 0, 0, 0, 0, 0, 0, 0, 0], [0, 0, 0, 0, 0, 0, 0, 0, 0], ["2", 0, 0, 0, 0, 0, 0, 0, "2"], [0, "2", 0, 0, 0, 0, 0, "2", 0], [0, 0, "2", 0, 0, 0, "2", 0, 0], [0, 0, 0, 8, 8, 8, 0, 0, 0], [8, 8, 8, 2, 2, 2, 8, 8, 8]]], "time": 11465}, {"action": {"tool": "check", "correct": true}, "grid": [[0, 0, 0, 0, 0, 0, 0, 0, 0], [0, 0, 0, 0, 0, 0, 0, 0, 0], [0, 0, 0, 0, 0, 0, 0, 0, 0], [0, 0, 0, 0, 0, 0, 0, 0, 0], [2, 0, 0, 0, 0, 0, 0, 0, 2], [0, 2, 0, 0, 0, 0, 0, 2, 0], [0, 0, 2, 0, 0, 0, 2, 0, 0], [0, 0, 0, 8, 8, 8, 0, 0, 0], [8, 8, 8, 2, 2, 2, 8, 8, 8]], "currentLayer": 0, "layer_list": [[[0, 0, 0, 0, 0, 0, 0, 0, 0], [0, 0, 0, 0, 0, 0, 0, 0, 0], [0, 0, 0, 0, 0, 0, 0, 0, 0], [0, 0, 0, 0, 0, 0, 0, 0, 0], ["2", 0, 0, 0, 0, 0, 0, 0, "2"], [0, "2", 0, 0, 0, 0, 0, "2", 0], [0, 0, "2", 0, 0, 0, "2", 0, 0], [0, 0, 0, 8, 8, 8, 0, 0, 0], [8, 8, 8, 2, 2, 2, 8, 8, 8]]], "time": 1353}]}