{"task": "ec883f72", "user_id": "l6exy1ty0ibgvbvdfgzt", "action_sequence": [{"action": {"tool": "change_example", "example": 1}, "grid": [[0, 0, 0], [0, 0, 0], [0, 0, 0]], "currentLayer": 0, "layer_list": [[[0, 0, 0], [0, 0, 0], [0, 0, 0]]], "time": 4628}, {"action": {"tool": "change_example", "example": 2}, "grid": [[0, 0, 0], [0, 0, 0], [0, 0, 0]], "currentLayer": 0, "layer_list": [[[0, 0, 0], [0, 0, 0], [0, 0, 0]]], "time": 943}, {"action": {"tool": "copyFromInput"}, "grid": [[0, 0, 0, 0, 3, 0, 4, 4, 0, 3, 0, 0], [0, 0, 0, 0, 3, 0, 4, 4, 0, 3, 0, 0], [0, 0, 0, 0, 3, 0, 4, 4, 0, 3, 0, 0], [0, 0, 0, 0, 3, 0, 0, 0, 0, 3, 0, 0], [0, 0, 0, 0, 3, 3, 3, 3, 3, 3, 0, 0], [0, 0, 0, 0, 0, 0, 0, 0, 0, 0, 0, 0], [0, 0, 0, 0, 0, 0, 0, 0, 0, 0, 0, 0], [0, 0, 0, 0, 0, 0, 0, 0, 0, 0, 0, 0], [0, 0, 0, 0, 0, 0, 0, 0, 0, 0, 0, 0], [0, 0, 0, 0, 0, 0, 0, 0, 0, 0, 0, 0], [0, 0, 0, 0, 0, 0, 0, 0, 0, 0, 0, 0], [0, 0, 0, 0, 0, 0, 0, 0, 0, 0, 0, 0]], "currentLayer": 0, "layer_list": [[[0, 0, 0, 0, 3, 0, 4, 4, 0, 3, 0, 0], [0, 0, 0, 0, 3, 0, 4, 4, 0, 3, 0, 0], [0, 0, 0, 0, 3, 0, 4, 4, 0, 3, 0, 0], [0, 0, 0, 0, 3, 0, 0, 0, 0, 3, 0, 0], [0, 0, 0, 0, 3, 3, 3, 3, 3, 3, 0, 0], [0, 0, 0, 0, 0, 0, 0, 0, 0, 0, 0, 0], [0, 0, 0, 0, 0, 0, 0, 0, 0, 0, 0, 0], [0, 0, 0, 0, 0, 0, 0, 0, 0, 0, 0, 0], [0, 0, 0, 0, 0, 0, 0, 0, 0, 0, 0, 0], [0, 0, 0, 0, 0, 0, 0, 0, 0, 0, 0, 0], [0, 0, 0, 0, 0, 0, 0, 0, 0, 0, 0, 0], [0, 0, 0, 0, 0, 0, 0, 0, 0, 0, 0, 0]]], "time": 1837}, {"action": {"tool": "edit", "symbol": "3", "row": "5", "col": "3"}, "grid": [[0, 0, 0, 0, 3, 0, 4, 4, 0, 3, 0, 0], [0, 0, 0, 0, 3, 0, 4, 4, 0, 3, 0, 0], [0, 0, 0, 0, 3, 0, 4, 4, 0, 3, 0, 0], [0, 0, 0, 0, 3, 0, 0, 0, 0, 3, 0, 0], [0, 0, 0, 0, 3, 3, 3, 3, 3, 3, 0, 0], [0, 0, 0, 3, 0, 0, 0, 0, 0, 0, 0, 0], [0, 0, 0, 0, 0, 0, 0, 0, 0, 0, 0, 0], [0, 0, 0, 0, 0, 0, 0, 0, 0, 0, 0, 0], [0, 0, 0, 0, 0, 0, 0, 0, 0, 0, 0, 0], [0, 0, 0, 0, 0, 0, 0, 0, 0, 0, 0, 0], [0, 0, 0, 0, 0, 0, 0, 0, 0, 0, 0, 0], [0, 0, 0, 0, 0, 0, 0, 0, 0, 0, 0, 0]], "currentLayer": 0, "layer_list": [[[0, 0, 0, 0, 3, 0, 4, 4, 0, 3, 0, 0], [0, 0, 0, 0, 3, 0, 4, 4, 0, 3, 0, 0], [0, 0, 0, 0, 3, 0, 4, 4, 0, 3, 0, 0], [0, 0, 0, 0, 3, 0, 0, 0, 0, 3, 0, 0], [0, 0, 0, 0, 3, 3, 3, 3, 3, 3, 0, 0], [0, 0, 0, "3", 0, 0, 0, 0, 0, 0, 0, 0], [0, 0, 0, 0, 0, 0, 0, 0, 0, 0, 0, 0], [0, 0, 0, 0, 0, 0, 0, 0, 0, 0, 0, 0], [0, 0, 0, 0, 0, 0, 0, 0, 0, 0, 0, 0], [0, 0, 0, 0, 0, 0, 0, 0, 0, 0, 0, 0], [0, 0, 0, 0, 0, 0, 0, 0, 0, 0, 0, 0], [0, 0, 0, 0, 0, 0, 0, 0, 0, 0, 0, 0]]], "time": 3549}, {"action": {"tool": "edit", "symbol": "3", "row": "6", "col": "2"}, "grid": [[0, 0, 0, 0, 3, 0, 4, 4, 0, 3, 0, 0], [0, 0, 0, 0, 3, 0, 4, 4, 0, 3, 0, 0], [0, 0, 0, 0, 3, 0, 4, 4, 0, 3, 0, 0], [0, 0, 0, 0, 3, 0, 0, 0, 0, 3, 0, 0], [0, 0, 0, 0, 3, 3, 3, 3, 3, 3, 0, 0], [0, 0, 0, 3, 0, 0, 0, 0, 0, 0, 0, 0], [0, 0, 3, 0, 0, 0, 0, 0, 0, 0, 0, 0], [0, 0, 0, 0, 0, 0, 0, 0, 0, 0, 0, 0], [0, 0, 0, 0, 0, 0, 0, 0, 0, 0, 0, 0], [0, 0, 0, 0, 0, 0, 0, 0, 0, 0, 0, 0], [0, 0, 0, 0, 0, 0, 0, 0, 0, 0, 0, 0], [0, 0, 0, 0, 0, 0, 0, 0, 0, 0, 0, 0]], "currentLayer": 0, "layer_list": [[[0, 0, 0, 0, 3, 0, 4, 4, 0, 3, 0, 0], [0, 0, 0, 0, 3, 0, 4, 4, 0, 3, 0, 0], [0, 0, 0, 0, 3, 0, 4, 4, 0, 3, 0, 0], [0, 0, 0, 0, 3, 0, 0, 0, 0, 3, 0, 0], [0, 0, 0, 0, 3, 3, 3, 3, 3, 3, 0, 0], [0, 0, 0, "3", 0, 0, 0, 0, 0, 0, 0, 0], [0, 0, "3", 0, 0, 0, 0, 0, 0, 0, 0, 0], [0, 0, 0, 0, 0, 0, 0, 0, 0, 0, 0, 0], [0, 0, 0, 0, 0, 0, 0, 0, 0, 0, 0, 0], [0, 0, 0, 0, 0, 0, 0, 0, 0, 0, 0, 0], [0, 0, 0, 0, 0, 0, 0, 0, 0, 0, 0, 0], [0, 0, 0, 0, 0, 0, 0, 0, 0, 0, 0, 0]]], "time": 564}, {"action": {"tool": "edit", "symbol": "4", "row": "5", "col": "3"}, "grid": [[0, 0, 0, 0, 3, 0, 4, 4, 0, 3, 0, 0], [0, 0, 0, 0, 3, 0, 4, 4, 0, 3, 0, 0], [0, 0, 0, 0, 3, 0, 4, 4, 0, 3, 0, 0], [0, 0, 0, 0, 3, 0, 0, 0, 0, 3, 0, 0], [0, 0, 0, 0, 3, 3, 3, 3, 3, 3, 0, 0], [0, 0, 0, 4, 0, 0, 0, 0, 0, 0, 0, 0], [0, 0, 3, 0, 0, 0, 0, 0, 0, 0, 0, 0], [0, 0, 0, 0, 0, 0, 0, 0, 0, 0, 0, 0], [0, 0, 0, 0, 0, 0, 0, 0, 0, 0, 0, 0], [0, 0, 0, 0, 0, 0, 0, 0, 0, 0, 0, 0], [0, 0, 0, 0, 0, 0, 0, 0, 0, 0, 0, 0], [0, 0, 0, 0, 0, 0, 0, 0, 0, 0, 0, 0]], "currentLayer": 0, "layer_list": [[[0, 0, 0, 0, 3, 0, 4, 4, 0, 3, 0, 0], [0, 0, 0, 0, 3, 0, 4, 4, 0, 3, 0, 0], [0, 0, 0, 0, 3, 0, 4, 4, 0, 3, 0, 0], [0, 0, 0, 0, 3, 0, 0, 0, 0, 3, 0, 0], [0, 0, 0, 0, 3, 3, 3, 3, 3, 3, 0, 0], [0, 0, 0, "4", 0, 0, 0, 0, 0, 0, 0, 0], [0, 0, "3", 0, 0, 0, 0, 0, 0, 0, 0, 0], [0, 0, 0, 0, 0, 0, 0, 0, 0, 0, 0, 0], [0, 0, 0, 0, 0, 0, 0, 0, 0, 0, 0, 0], [0, 0, 0, 0, 0, 0, 0, 0, 0, 0, 0, 0], [0, 0, 0, 0, 0, 0, 0, 0, 0, 0, 0, 0], [0, 0, 0, 0, 0, 0, 0, 0, 0, 0, 0, 0]]], "time": 2836}, {"action": {"tool": "edit", "symbol": "4", "row": "6", "col": "3"}, "grid": [[0, 0, 0, 0, 3, 0, 4, 4, 0, 3, 0, 0], [0, 0, 0, 0, 3, 0, 4, 4, 0, 3, 0, 0], [0, 0, 0, 0, 3, 0, 4, 4, 0, 3, 0, 0], [0, 0, 0, 0, 3, 0, 0, 0, 0, 3, 0, 0], [0, 0, 0, 0, 3, 3, 3, 3, 3, 3, 0, 0], [0, 0, 0, 4, 0, 0, 0, 0, 0, 0, 0, 0], [0, 0, 3, 4, 0, 0, 0, 0, 0, 0, 0, 0], [0, 0, 0, 0, 0, 0, 0, 0, 0, 0, 0, 0], [0, 0, 0, 0, 0, 0, 0, 0, 0, 0, 0, 0], [0, 0, 0, 0, 0, 0, 0, 0, 0, 0, 0, 0], [0, 0, 0, 0, 0, 0, 0, 0, 0, 0, 0, 0], [0, 0, 0, 0, 0, 0, 0, 0, 0, 0, 0, 0]], "currentLayer": 0, "layer_list": [[[0, 0, 0, 0, 3, 0, 4, 4, 0, 3, 0, 0], [0, 0, 0, 0, 3, 0, 4, 4, 0, 3, 0, 0], [0, 0, 0, 0, 3, 0, 4, 4, 0, 3, 0, 0], [0, 0, 0, 0, 3, 0, 0, 0, 0, 3, 0, 0], [0, 0, 0, 0, 3, 3, 3, 3, 3, 3, 0, 0], [0, 0, 0, "4", 0, 0, 0, 0, 0, 0, 0, 0], [0, 0, "3", "4", 0, 0, 0, 0, 0, 0, 0, 0], [0, 0, 0, 0, 0, 0, 0, 0, 0, 0, 0, 0], [0, 0, 0, 0, 0, 0, 0, 0, 0, 0, 0, 0], [0, 0, 0, 0, 0, 0, 0, 0, 0, 0, 0, 0], [0, 0, 0, 0, 0, 0, 0, 0, 0, 0, 0, 0], [0, 0, 0, 0, 0, 0, 0, 0, 0, 0, 0, 0]]], "time": 394}, {"action": {"tool": "edit", "symbol": "4", "row": "6", "col": "3"}, "grid": [[0, 0, 0, 0, 3, 0, 4, 4, 0, 3, 0, 0], [0, 0, 0, 0, 3, 0, 4, 4, 0, 3, 0, 0], [0, 0, 0, 0, 3, 0, 4, 4, 0, 3, 0, 0], [0, 0, 0, 0, 3, 0, 0, 0, 0, 3, 0, 0], [0, 0, 0, 0, 3, 3, 3, 3, 3, 3, 0, 0], [0, 0, 0, 4, 0, 0, 0, 0, 0, 0, 0, 0], [0, 0, 3, 4, 0, 0, 0, 0, 0, 0, 0, 0], [0, 0, 0, 0, 0, 0, 0, 0, 0, 0, 0, 0], [0, 0, 0, 0, 0, 0, 0, 0, 0, 0, 0, 0], [0, 0, 0, 0, 0, 0, 0, 0, 0, 0, 0, 0], [0, 0, 0, 0, 0, 0, 0, 0, 0, 0, 0, 0], [0, 0, 0, 0, 0, 0, 0, 0, 0, 0, 0, 0]], "currentLayer": 0, "layer_list": [[[0, 0, 0, 0, 3, 0, 4, 4, 0, 3, 0, 0], [0, 0, 0, 0, 3, 0, 4, 4, 0, 3, 0, 0], [0, 0, 0, 0, 3, 0, 4, 4, 0, 3, 0, 0], [0, 0, 0, 0, 3, 0, 0, 0, 0, 3, 0, 0], [0, 0, 0, 0, 3, 3, 3, 3, 3, 3, 0, 0], [0, 0, 0, "4", 0, 0, 0, 0, 0, 0, 0, 0], [0, 0, "3", "4", 0, 0, 0, 0, 0, 0, 0, 0], [0, 0, 0, 0, 0, 0, 0, 0, 0, 0, 0, 0], [0, 0, 0, 0, 0, 0, 0, 0, 0, 0, 0, 0], [0, 0, 0, 0, 0, 0, 0, 0, 0, 0, 0, 0], [0, 0, 0, 0, 0, 0, 0, 0, 0, 0, 0, 0], [0, 0, 0, 0, 0, 0, 0, 0, 0, 0, 0, 0]]], "time": 597}, {"action": {"tool": "edit", "symbol": "4", "row": "6", "col": "2"}, "grid": [[0, 0, 0, 0, 3, 0, 4, 4, 0, 3, 0, 0], [0, 0, 0, 0, 3, 0, 4, 4, 0, 3, 0, 0], [0, 0, 0, 0, 3, 0, 4, 4, 0, 3, 0, 0], [0, 0, 0, 0, 3, 0, 0, 0, 0, 3, 0, 0], [0, 0, 0, 0, 3, 3, 3, 3, 3, 3, 0, 0], [0, 0, 0, 4, 0, 0, 0, 0, 0, 0, 0, 0], [0, 0, 4, 4, 0, 0, 0, 0, 0, 0, 0, 0], [0, 0, 0, 0, 0, 0, 0, 0, 0, 0, 0, 0], [0, 0, 0, 0, 0, 0, 0, 0, 0, 0, 0, 0], [0, 0, 0, 0, 0, 0, 0, 0, 0, 0, 0, 0], [0, 0, 0, 0, 0, 0, 0, 0, 0, 0, 0, 0], [0, 0, 0, 0, 0, 0, 0, 0, 0, 0, 0, 0]], "currentLayer": 0, "layer_list": [[[0, 0, 0, 0, 3, 0, 4, 4, 0, 3, 0, 0], [0, 0, 0, 0, 3, 0, 4, 4, 0, 3, 0, 0], [0, 0, 0, 0, 3, 0, 4, 4, 0, 3, 0, 0], [0, 0, 0, 0, 3, 0, 0, 0, 0, 3, 0, 0], [0, 0, 0, 0, 3, 3, 3, 3, 3, 3, 0, 0], [0, 0, 0, "4", 0, 0, 0, 0, 0, 0, 0, 0], [0, 0, "4", "4", 0, 0, 0, 0, 0, 0, 0, 0], [0, 0, 0, 0, 0, 0, 0, 0, 0, 0, 0, 0], [0, 0, 0, 0, 0, 0, 0, 0, 0, 0, 0, 0], [0, 0, 0, 0, 0, 0, 0, 0, 0, 0, 0, 0], [0, 0, 0, 0, 0, 0, 0, 0, 0, 0, 0, 0], [0, 0, 0, 0, 0, 0, 0, 0, 0, 0, 0, 0]]], "time": 382}, {"action": {"tool": "edit", "symbol": "4", "row": "7", "col": "1"}, "grid": [[0, 0, 0, 0, 3, 0, 4, 4, 0, 3, 0, 0], [0, 0, 0, 0, 3, 0, 4, 4, 0, 3, 0, 0], [0, 0, 0, 0, 3, 0, 4, 4, 0, 3, 0, 0], [0, 0, 0, 0, 3, 0, 0, 0, 0, 3, 0, 0], [0, 0, 0, 0, 3, 3, 3, 3, 3, 3, 0, 0], [0, 0, 0, 4, 0, 0, 0, 0, 0, 0, 0, 0], [0, 0, 4, 4, 0, 0, 0, 0, 0, 0, 0, 0], [0, 4, 0, 0, 0, 0, 0, 0, 0, 0, 0, 0], [0, 0, 0, 0, 0, 0, 0, 0, 0, 0, 0, 0], [0, 0, 0, 0, 0, 0, 0, 0, 0, 0, 0, 0], [0, 0, 0, 0, 0, 0, 0, 0, 0, 0, 0, 0], [0, 0, 0, 0, 0, 0, 0, 0, 0, 0, 0, 0]], "currentLayer": 0, "layer_list": [[[0, 0, 0, 0, 3, 0, 4, 4, 0, 3, 0, 0], [0, 0, 0, 0, 3, 0, 4, 4, 0, 3, 0, 0], [0, 0, 0, 0, 3, 0, 4, 4, 0, 3, 0, 0], [0, 0, 0, 0, 3, 0, 0, 0, 0, 3, 0, 0], [0, 0, 0, 0, 3, 3, 3, 3, 3, 3, 0, 0], [0, 0, 0, "4", 0, 0, 0, 0, 0, 0, 0, 0], [0, 0, "4", "4", 0, 0, 0, 0, 0, 0, 0, 0], [0, "4", 0, 0, 0, 0, 0, 0, 0, 0, 0, 0], [0, 0, 0, 0, 0, 0, 0, 0, 0, 0, 0, 0], [0, 0, 0, 0, 0, 0, 0, 0, 0, 0, 0, 0], [0, 0, 0, 0, 0, 0, 0, 0, 0, 0, 0, 0], [0, 0, 0, 0, 0, 0, 0, 0, 0, 0, 0, 0]]], "time": 626}, {"action": {"tool": "edit", "symbol": "4", "row": "8", "col": "0"}, "grid": [[0, 0, 0, 0, 3, 0, 4, 4, 0, 3, 0, 0], [0, 0, 0, 0, 3, 0, 4, 4, 0, 3, 0, 0], [0, 0, 0, 0, 3, 0, 4, 4, 0, 3, 0, 0], [0, 0, 0, 0, 3, 0, 0, 0, 0, 3, 0, 0], [0, 0, 0, 0, 3, 3, 3, 3, 3, 3, 0, 0], [0, 0, 0, 4, 0, 0, 0, 0, 0, 0, 0, 0], [0, 0, 4, 4, 0, 0, 0, 0, 0, 0, 0, 0], [0, 4, 0, 0, 0, 0, 0, 0, 0, 0, 0, 0], [4, 0, 0, 0, 0, 0, 0, 0, 0, 0, 0, 0], [0, 0, 0, 0, 0, 0, 0, 0, 0, 0, 0, 0], [0, 0, 0, 0, 0, 0, 0, 0, 0, 0, 0, 0], [0, 0, 0, 0, 0, 0, 0, 0, 0, 0, 0, 0]], "currentLayer": 0, "layer_list": [[[0, 0, 0, 0, 3, 0, 4, 4, 0, 3, 0, 0], [0, 0, 0, 0, 3, 0, 4, 4, 0, 3, 0, 0], [0, 0, 0, 0, 3, 0, 4, 4, 0, 3, 0, 0], [0, 0, 0, 0, 3, 0, 0, 0, 0, 3, 0, 0], [0, 0, 0, 0, 3, 3, 3, 3, 3, 3, 0, 0], [0, 0, 0, "4", 0, 0, 0, 0, 0, 0, 0, 0], [0, 0, "4", "4", 0, 0, 0, 0, 0, 0, 0, 0], [0, "4", 0, 0, 0, 0, 0, 0, 0, 0, 0, 0], ["4", 0, 0, 0, 0, 0, 0, 0, 0, 0, 0, 0], [0, 0, 0, 0, 0, 0, 0, 0, 0, 0, 0, 0], [0, 0, 0, 0, 0, 0, 0, 0, 0, 0, 0, 0], [0, 0, 0, 0, 0, 0, 0, 0, 0, 0, 0, 0]]], "time": 543}, {"action": {"tool": "edit", "symbol": "4", "row": "5", "col": "10"}, "grid": [[0, 0, 0, 0, 3, 0, 4, 4, 0, 3, 0, 0], [0, 0, 0, 0, 3, 0, 4, 4, 0, 3, 0, 0], [0, 0, 0, 0, 3, 0, 4, 4, 0, 3, 0, 0], [0, 0, 0, 0, 3, 0, 0, 0, 0, 3, 0, 0], [0, 0, 0, 0, 3, 3, 3, 3, 3, 3, 0, 0], [0, 0, 0, 4, 0, 0, 0, 0, 0, 0, 4, 0], [0, 0, 4, 4, 0, 0, 0, 0, 0, 0, 0, 0], [0, 4, 0, 0, 0, 0, 0, 0, 0, 0, 0, 0], [4, 0, 0, 0, 0, 0, 0, 0, 0, 0, 0, 0], [0, 0, 0, 0, 0, 0, 0, 0, 0, 0, 0, 0], [0, 0, 0, 0, 0, 0, 0, 0, 0, 0, 0, 0], [0, 0, 0, 0, 0, 0, 0, 0, 0, 0, 0, 0]], "currentLayer": 0, "layer_list": [[[0, 0, 0, 0, 3, 0, 4, 4, 0, 3, 0, 0], [0, 0, 0, 0, 3, 0, 4, 4, 0, 3, 0, 0], [0, 0, 0, 0, 3, 0, 4, 4, 0, 3, 0, 0], [0, 0, 0, 0, 3, 0, 0, 0, 0, 3, 0, 0], [0, 0, 0, 0, 3, 3, 3, 3, 3, 3, 0, 0], [0, 0, 0, "4", 0, 0, 0, 0, 0, 0, "4", 0], [0, 0, "4", "4", 0, 0, 0, 0, 0, 0, 0, 0], [0, "4", 0, 0, 0, 0, 0, 0, 0, 0, 0, 0], ["4", 0, 0, 0, 0, 0, 0, 0, 0, 0, 0, 0], [0, 0, 0, 0, 0, 0, 0, 0, 0, 0, 0, 0], [0, 0, 0, 0, 0, 0, 0, 0, 0, 0, 0, 0], [0, 0, 0, 0, 0, 0, 0, 0, 0, 0, 0, 0]]], "time": 674}, {"action": {"tool": "edit", "symbol": "4", "row": "6", "col": "11"}, "grid": [[0, 0, 0, 0, 3, 0, 4, 4, 0, 3, 0, 0], [0, 0, 0, 0, 3, 0, 4, 4, 0, 3, 0, 0], [0, 0, 0, 0, 3, 0, 4, 4, 0, 3, 0, 0], [0, 0, 0, 0, 3, 0, 0, 0, 0, 3, 0, 0], [0, 0, 0, 0, 3, 3, 3, 3, 3, 3, 0, 0], [0, 0, 0, 4, 0, 0, 0, 0, 0, 0, 4, 0], [0, 0, 4, 4, 0, 0, 0, 0, 0, 0, 0, 4], [0, 4, 0, 0, 0, 0, 0, 0, 0, 0, 0, 0], [4, 0, 0, 0, 0, 0, 0, 0, 0, 0, 0, 0], [0, 0, 0, 0, 0, 0, 0, 0, 0, 0, 0, 0], [0, 0, 0, 0, 0, 0, 0, 0, 0, 0, 0, 0], [0, 0, 0, 0, 0, 0, 0, 0, 0, 0, 0, 0]], "currentLayer": 0, "layer_list": [[[0, 0, 0, 0, 3, 0, 4, 4, 0, 3, 0, 0], [0, 0, 0, 0, 3, 0, 4, 4, 0, 3, 0, 0], [0, 0, 0, 0, 3, 0, 4, 4, 0, 3, 0, 0], [0, 0, 0, 0, 3, 0, 0, 0, 0, 3, 0, 0], [0, 0, 0, 0, 3, 3, 3, 3, 3, 3, 0, 0], [0, 0, 0, "4", 0, 0, 0, 0, 0, 0, "4", 0], [0, 0, "4", "4", 0, 0, 0, 0, 0, 0, 0, "4"], [0, "4", 0, 0, 0, 0, 0, 0, 0, 0, 0, 0], ["4", 0, 0, 0, 0, 0, 0, 0, 0, 0, 0, 0], [0, 0, 0, 0, 0, 0, 0, 0, 0, 0, 0, 0], [0, 0, 0, 0, 0, 0, 0, 0, 0, 0, 0, 0], [0, 0, 0, 0, 0, 0, 0, 0, 0, 0, 0, 0]]], "time": 614}, {"action": {"tool": "edit", "symbol": "0", "row": "6", "col": "3"}, "grid": [[0, 0, 0, 0, 3, 0, 4, 4, 0, 3, 0, 0], [0, 0, 0, 0, 3, 0, 4, 4, 0, 3, 0, 0], [0, 0, 0, 0, 3, 0, 4, 4, 0, 3, 0, 0], [0, 0, 0, 0, 3, 0, 0, 0, 0, 3, 0, 0], [0, 0, 0, 0, 3, 3, 3, 3, 3, 3, 0, 0], [0, 0, 0, 4, 0, 0, 0, 0, 0, 0, 4, 0], [0, 0, 4, 0, 0, 0, 0, 0, 0, 0, 0, 4], [0, 4, 0, 0, 0, 0, 0, 0, 0, 0, 0, 0], [4, 0, 0, 0, 0, 0, 0, 0, 0, 0, 0, 0], [0, 0, 0, 0, 0, 0, 0, 0, 0, 0, 0, 0], [0, 0, 0, 0, 0, 0, 0, 0, 0, 0, 0, 0], [0, 0, 0, 0, 0, 0, 0, 0, 0, 0, 0, 0]], "currentLayer": 0, "layer_list": [[[0, 0, 0, 0, 3, 0, 4, 4, 0, 3, 0, 0], [0, 0, 0, 0, 3, 0, 4, 4, 0, 3, 0, 0], [0, 0, 0, 0, 3, 0, 4, 4, 0, 3, 0, 0], [0, 0, 0, 0, 3, 0, 0, 0, 0, 3, 0, 0], [0, 0, 0, 0, 3, 3, 3, 3, 3, 3, 0, 0], [0, 0, 0, "4", 0, 0, 0, 0, 0, 0, "4", 0], [0, 0, "4", 0, 0, 0, 0, 0, 0, 0, 0, "4"], [0, "4", 0, 0, 0, 0, 0, 0, 0, 0, 0, 0], ["4", 0, 0, 0, 0, 0, 0, 0, 0, 0, 0, 0], [0, 0, 0, 0, 0, 0, 0, 0, 0, 0, 0, 0], [0, 0, 0, 0, 0, 0, 0, 0, 0, 0, 0, 0], [0, 0, 0, 0, 0, 0, 0, 0, 0, 0, 0, 0]]], "time": 2068}, {"action": {"tool": "check", "correct": true}, "grid": [[0, 0, 0, 0, 3, 0, 4, 4, 0, 3, 0, 0], [0, 0, 0, 0, 3, 0, 4, 4, 0, 3, 0, 0], [0, 0, 0, 0, 3, 0, 4, 4, 0, 3, 0, 0], [0, 0, 0, 0, 3, 0, 0, 0, 0, 3, 0, 0], [0, 0, 0, 0, 3, 3, 3, 3, 3, 3, 0, 0], [0, 0, 0, 4, 0, 0, 0, 0, 0, 0, 4, 0], [0, 0, 4, 0, 0, 0, 0, 0, 0, 0, 0, 4], [0, 4, 0, 0, 0, 0, 0, 0, 0, 0, 0, 0], [4, 0, 0, 0, 0, 0, 0, 0, 0, 0, 0, 0], [0, 0, 0, 0, 0, 0, 0, 0, 0, 0, 0, 0], [0, 0, 0, 0, 0, 0, 0, 0, 0, 0, 0, 0], [0, 0, 0, 0, 0, 0, 0, 0, 0, 0, 0, 0]], "currentLayer": 0, "layer_list": [[[0, 0, 0, 0, 3, 0, 4, 4, 0, 3, 0, 0], [0, 0, 0, 0, 3, 0, 4, 4, 0, 3, 0, 0], [0, 0, 0, 0, 3, 0, 4, 4, 0, 3, 0, 0], [0, 0, 0, 0, 3, 0, 0, 0, 0, 3, 0, 0], [0, 0, 0, 0, 3, 3, 3, 3, 3, 3, 0, 0], [0, 0, 0, "4", 0, 0, 0, 0, 0, 0, "4", 0], [0, 0, "4", 0, 0, 0, 0, 0, 0, 0, 0, "4"], [0, "4", 0, 0, 0, 0, 0, 0, 0, 0, 0, 0], ["4", 0, 0, 0, 0, 0, 0, 0, 0, 0, 0, 0], [0, 0, 0, 0, 0, 0, 0, 0, 0, 0, 0, 0], [0, 0, 0, 0, 0, 0, 0, 0, 0, 0, 0, 0], [0, 0, 0, 0, 0, 0, 0, 0, 0, 0, 0, 0]]], "time": 1321}]}